project 6/bcd_counter.sv
module bcd_counter (
    input logic clk,
    input logic reset,
    input logic enable,

    output logic [3:0] count
);

    always_ff @(posedge clk or posedge reset) begin
        if (reset) begin
            count <= 4'd0;
        end else if (enable) begin
            if (count == 4'd9) begin
                count <= 4'd0;
            end else begin
                count <= count + 4'd1;
            end
        end
    end
endmodule

project 6/bcd_counter_tb.sv
module bcd_counter_tb;
    logic clk, reset, enable;
    logic [3:0] count, expected_count;
    int errors;

    bcd_counter dut(
        .clk(clk),
        .reset(reset),
        .enable(enable),
        .count(count)
    );

    initial clk = 1'b0;
    always #5 clk = ~clk;

    initial begin
        $dumpfile("bcd_counter_tb.vcd");
        $dumpvars(0, bcd_counter_tb);

        reset = 1'b1;
        enable = 1'b0;

        expected_count = 4'd0;
        errors = 0;

        #1;
        if (count !== expected_count) begin
            $display("ERROR after reset at time %0t: expected=%0d got=%0d", $time, expected_count, count);
            errors++;
        end else begin
            $display("PASS after reset at time %0t: count=%0d", $time, count);
        end

        @(negedge clk);
        reset = 1'b0;

        @(negedge clk);
        enable = 1'b1;

        for (int i = 0; i < 12; i++) begin
            @(posedge clk);
            #1;

            if (expected_count == 4'd9) begin
                expected_count = 4'd0;
            end else begin
                expected_count = expected_count + 4'd1;
            end

            if (count !== expected_count) begin
                $display("ERROR count cycle %0d at time %0t: expected=%0d got=%0d", i, $time, expected_count, count);
                errors++;
            end else begin
                $display("PASS count cycle %0d at time %0t: count=%0d", i, $time, count);
            end
        end

        @(negedge clk);
        enable = 1'b0;

        for (int i = 0; i < 3; i++) begin
            @(posedge clk);
            #1;

            if (count !== expected_count) begin
                $display("ERROR hold cycle %0d at time %0t: expected=%0d got=%0d", i, $time, expected_count, count);
                errors++;
            end else begin
                $display("PASS hold cycle %0d at time %0t: count held at %0d", i, $time, count);
            end
        end

        if (errors == 0) begin
            $display("TEST PASSED: bcd_counter behaved as expected");
        end else begin
            $display("TEST FAILED: %0d error(s)", errors);
        end

        $finish;
    end

endmodule

project 6/bcd_counter_tb.vcd
$date
	Fri Jun 19 11:32:33 2026
$end
$version
	Icarus Verilog
$end
$timescale
	1s
$end
$scope module bcd_counter_tb $end
$var wire 4 ! count [3:0] $end
$var reg 1 " clk $end
$var reg 1 # enable $end
$var reg 4 $ expected_count [3:0] $end
$var reg 1 % reset $end
$var integer 32 & errors [31:0] $end
$scope module dut $end
$var wire 1 " clk $end
$var wire 1 # enable $end
$var wire 1 % reset $end
$var reg 4 ' count [3:0] $end
$upscope $end
$scope begin $ivl_for_loop0 $end
$var integer 32 ( i [31:0] $end
$upscope $end
$scope begin $ivl_for_loop1 $end
$var integer 32 ) i [31:0] $end
$upscope $end
$upscope $end
$enddefinitions $end
$comment Show the parameter values. $end
$dumpall
$end
#0
$dumpvars
b0 )
b0 (
b0 '
b0 &
1%
b0 $
0#
0"
b0 !
$end
#5
1"
#10
0%
0"
#15
1"
#20
1#
0"
#25
b1 !
b1 '
1"
#26
b1 (
b1 $
#30
0"
#35
b10 !
b10 '
1"
#36
b10 (
b10 $
#40
0"
#45
b11 !
b11 '
1"
#46
b11 (
b11 $
#50
0"
#55
b100 !
b100 '
1"
#56
b100 (
b100 $
#60
0"
#65
b101 !
b101 '
1"
#66
b101 (
b101 $
#70
0"
#75
b110 !
b110 '
1"
#76
b110 (
b110 $
#80
0"
#85
b111 !
b111 '
1"
#86
b111 (
b111 $
#90
0"
#95
b1000 !
b1000 '
1"
#96
b1000 (
b1000 $
#100
0"
#105
b1001 !
b1001 '
1"
#106
b1001 (
b1001 $
#110
0"
#115
b0 !
b0 '
1"
#116
b1010 (
b0 $
#120
0"
#125
b1 !
b1 '
1"
#126
b1011 (
b1 $
#130
0"
#135
b10 !
b10 '
1"
#136
b1100 (
b10 $
#140
0#
0"
#145
1"
#146
b1 )
#150
0"
#155
1"
#156
b10 )
#160
0"
#165
1"
#166
b11 )
