project 6/seven_seg_decoder/seven_seg_decoder.sv
module seven_seg_decoder(
    input logic [3:0] count,
    output logic [6:0] seg
);

    always_comb begin
        case (count)
            4'd0: seg = 7'b1111110; // a,b,c,d,e,f on; g off
            4'd1: seg = 7'b0110000; // b,c on
            4'd2: seg = 7'b1101101; // a,b,d,e,g on
            4'd3: seg = 7'b1111001; // a,b,c,d,g on
            4'd4: seg = 7'b0110011; // b,c,f,g on
            4'd5: seg = 7'b1011011; // a,c,d,f,g on
            4'd6: seg = 7'b1011111; // a,c,d,e,f,g on
            4'd7: seg = 7'b1110000; // a,b,c on
            4'd8: seg = 7'b1111111; // all on
            4'd9: seg = 7'b1111011; // a,b,c,d,f,g on
            default: seg = 7'b0000000;
        endcase
    end
endmodule

project 6/seven_seg_decoder/seven_seg_decoder_tb.sv
module seven_seg_decoder_tb;
    logic [3:0] count;
    logic [6:0] seg, expected_seg;
    int errors;

    seven_seg_decoder dut(
        .count(count),
        .seg(seg)
    );

    task automatic check_digit(input logic [3:0] digit, input logic [6:0] expected);
        begin
            count = digit;
            expected_seg = expected;
            #1;

            if (seg !== expected_seg) begin
                $display("ERROR digit=%0d: expected=%b got=%b", digit, expected_seg, seg);
                errors++;
            end else begin
                $display("PASS digit=%0d: seg=%b", digit, seg);
            end
        end
    endtask

    initial begin
        $dumpfile("seven_seg_decoder_tb.vcd");
        $dumpvars(0, seven_seg_decoder_tb);

        errors = 0;

        check_digit(4'd0, 7'b1111110);
        check_digit(4'd1, 7'b0110000);
        check_digit(4'd2, 7'b1101101);
        check_digit(4'd3, 7'b1111001);
        check_digit(4'd4, 7'b0110011);
        check_digit(4'd5, 7'b1011011);
        check_digit(4'd6, 7'b1011111);
        check_digit(4'd7, 7'b1110000);
        check_digit(4'd8, 7'b1111111);
        check_digit(4'd9, 7'b1111011);

        // Invalid BCD input should blank the display
        check_digit(4'd10, 7'b0000000);

        if (errors == 0) begin
            $display("TEST PASSED: seven_seg_decoder behaved as expected");
        end else begin
            $display("TEST FAILED: %0d error(s)", errors);
        end

        #10;
        $finish;
    end
endmodule

project 6/seven_seg_decoder_tb.vcd
$date
	Mon Jun 22 09:09:57 2026
$end
$version
	Icarus Verilog
$end
$timescale
	1s
$end
$scope module seven_seg_decoder_tb $end
$var wire 7 ! seg [6:0] $end
$var reg 4 " count [3:0] $end
$var reg 7 # expected_seg [6:0] $end
$var integer 32 $ errors [31:0] $end
$scope module dut $end
$var wire 4 % count [3:0] $end
$var reg 7 & seg [6:0] $end
$upscope $end
$scope task check_digit $end
$upscope $end
$upscope $end
$enddefinitions $end
$comment Show the parameter values. $end
$dumpall
$end
#0
$dumpvars
b1111110 &
b0 %
b0 $
b1111110 #
b0 "
b1111110 !
$end
#1
b110000 !
b110000 &
b110000 #
b1 "
b1 %
#2
b1101101 !
b1101101 &
b1101101 #
b10 "
b10 %
#3
b1111001 !
b1111001 &
b1111001 #
b11 "
b11 %
#4
b110011 !
b110011 &
b110011 #
b100 "
b100 %
#5
b1011011 !
b1011011 &
b1011011 #
b101 "
b101 %
#6
b1011111 !
b1011111 &
b1011111 #
b110 "
b110 %
#7
b1110000 !
b1110000 &
b1110000 #
b111 "
b111 %
#8
b1111111 !
b1111111 &
b1111111 #
b1000 "
b1000 %
#9
b1111011 !
b1111011 &
b1111011 #
b1001 "
b1001 %
#10
b0 !
b0 &
b0 #
b1010 "
b1010 %
