project 5/vending_machine_controller.v
module vending_machine_fsm (
    input wire clk,
    input wire reset,
    input wire nickel,
    input wire dime,
    input wire quarter,
    output reg dispense,
    output reg return_change
);

    // states
    localparam S0 = 3'b000;
    localparam S5 = 3'b001;
    localparam S10 = 3'b010;
    localparam S15 = 3'b011;
    localparam S20 = 3'b100;
    localparam DISPENSE = 3'b101;
    localparam DISPENSE_CHANGE = 3'b110;

    reg [2:0] state;
    reg [2:0] next_state;

    // state logic
    always @(posedge clk or posedge reset) begin
        if (reset) begin
            state <= S0;
        end
        else begin
            state <= next_state;
        end
    end

    // next_state logic
    always @(*) begin
        next_state = state; // in case no coin is inserted

        case (state)
            S0: begin
                if (nickel) begin
                    next_state = S5;
                end 
                else if (dime) begin
                    next_state = S10;
                end
                else if (quarter) begin
                    next_state = DISPENSE;
                end
            end

            S5: begin
                if (nickel) begin
                    next_state = S10;
                end
                else if (dime) begin
                    next_state = S15;
                end
                else if (quarter) begin
                    next_state = DISPENSE_CHANGE;
                end
            end

            S10 : begin
                if (nickel) begin
                    next_state = S15;
                end
                else if (dime) begin
                    next_state = S20;
                end
                else if (quarter) begin
                    next_state = DISPENSE_CHANGE;
                end
            end

            S15: begin
                if (nickel) begin
                    next_state = S20;
                end
                else if (dime) begin
                    next_state = DISPENSE;
                end
                else if (quarter) begin
                    next_state = DISPENSE_CHANGE;
                end
            end

            S20: begin
                if (nickel) begin
                    next_state = DISPENSE;
                end
                else if (dime) begin
                    next_state = DISPENSE_CHANGE;
                end
                else if (quarter) begin
                    next_state = DISPENSE_CHANGE;
                end
            end

            DISPENSE: begin
                next_state = S0;
            end

            DISPENSE_CHANGE: begin
                next_state = S0;
            end

            default: begin
                next_state = S0;
            end
        endcase
    end

    // output logic
    always @(*) begin
        case (state)
            DISPENSE: begin
                dispense = 1'b1;
                return_change = 1'b0;
            end

            DISPENSE_CHANGE: begin
                dispense = 1'b1;
                return_change = 1'b1;
            end

            default: begin
                dispense = 1'b0;
                return_change = 1'b0;
            end
        endcase
    end
endmodule

project 5/vending_machine_controller_tb.v
`timescale 1ns / 1ps

module vending_machine_controller_tb;
    reg clk;
    reg reset;
    reg nickel;
    reg dime;
    reg quarter;

    wire dispense;
    wire return_change;

    vending_machine_fsm dut (
        .clk(clk),
        .reset(reset),
        .nickel(nickel),
        .dime(dime),
        .quarter(quarter),
        .dispense(dispense),
        .return_change(return_change)
    );

    initial begin
        clk = 1'b0;
    end

    always #5 clk = ~clk;
    initial begin
        $dumpfile("vending_machine_controller_tb.vcd");
        $dumpvars(0, vending_machine_controller_tb);

        $display("time\treset\tnickel\tdime\tquarter\tstate\tnext_state\tdispense\treturn_change");
        $monitor("%0t\t%b\t%b\t%b\t%b\t%b\t%b\t%b\t\t%b",
                 $time, reset, nickel, dime, quarter,
                 dut.state, dut.next_state, dispense, return_change);

        reset   = 1'b1;
        nickel  = 1'b0;
        dime    = 1'b0;
        quarter = 1'b0;

        #20;
        reset = 1'b0;

        $display("\n--- Test 1: quarter only -> expect dispense=1, return_change=0 ---");
         // Test 1: quarter only -> DISPENSE, no change
        #10;
        quarter = 1'b1;
        #10;
        quarter = 1'b0;

        #10;
        $display("CHECK Test 1 at time %0t: dispense=%b return_change=%b", $time, dispense, return_change);

        #20;

        $display("\n--- Test 2: nickel + quarter -> expect dispense=1, return_change=1 ---");
        // Test 2: nickel + quarter -> DISPENSE_CHANGE
        nickel = 1'b1;
        #10;
        nickel = 1'b0;

        #10;
        quarter = 1'b1;
        #10;
        quarter = 1'b0;

        #10;
        $display("CHECK Test 2 at time %0t: dispense=%b return_change=%b", $time, dispense, return_change);

        #20;

        $display("\n--- Test 3: dime + dime + nickel -> expect dispense=1, return_change=0 ---");
        // Test 3: dime + dime + nickel -> DISPENSE, no change
        dime = 1'b1;
        #10;
        dime = 1'b0;

        #10;
        dime = 1'b1;
        #10;
        dime = 1'b0;

        #10;
        nickel = 1'b1;
        #10;
        nickel = 1'b0;

        #10;
        $display("CHECK Test 3 at time %0t: dispense=%b return_change=%b", $time, dispense, return_change);

        #20;

        $display("\n--- Test 4: dime + quarter -> expect dispense=1, return_change=1 ---");
        // Test 4: dime + quarter -> DISPENSE_CHANGE
        dime = 1'b1;
        #10;
        dime = 1'b0;

        #10;
        quarter = 1'b1;
        #10;
        quarter = 1'b0;

        #10;
        $display("CHECK Test 4 at time %0t: dispense=%b return_change=%b", $time, dispense, return_change);

        #40;

        $finish;


    end


endmodule

project 5/vending_machine_controller_tb.vcd
$date
	Thu Jun 18 10:00:05 2026
$end
$version
	Icarus Verilog
$end
$timescale
	1ps
$end
$scope module vending_machine_controller_tb $end
$var wire 1 ! return_change $end
$var wire 1 " dispense $end
$var reg 1 # clk $end
$var reg 1 $ dime $end
$var reg 1 % nickel $end
$var reg 1 & quarter $end
$var reg 1 ' reset $end
$scope module dut $end
$var wire 1 # clk $end
$var wire 1 $ dime $end
$var wire 1 % nickel $end
$var wire 1 & quarter $end
$var wire 1 ' reset $end
$var parameter 3 ( DISPENSE $end
$var parameter 3 ) DISPENSE_CHANGE $end
$var parameter 3 * S0 $end
$var parameter 3 + S10 $end
$var parameter 3 , S15 $end
$var parameter 3 - S20 $end
$var parameter 3 . S5 $end
$var reg 1 " dispense $end
$var reg 3 / next_state [2:0] $end
$var reg 1 ! return_change $end
$var reg 3 0 state [2:0] $end
$upscope $end
$upscope $end
$enddefinitions $end
$comment Show the parameter values. $end
$dumpall
b1 .
b100 -
b11 ,
b10 +
b0 *
b110 )
b101 (
$end
#0
$dumpvars
b0 0
b0 /
1'
0&
0%
0$
0#
0"
0!
$end
#5000
1#
#10000
0#
#15000
1#
#20000
0#
0'
#25000
1#
#30000
b101 /
0#
1&
#35000
1"
b0 /
b101 0
1#
#40000
b0 /
0#
0&
#45000
0"
b0 0
1#
#50000
0#
#55000
1#
#60000
0#
#65000
1#
#70000
b1 /
0#
1%
#75000
b10 /
b1 0
1#
#80000
b1 /
0#
0%
#85000
1#
#90000
b110 /
0#
1&
#95000
1!
1"
b0 /
b110 0
1#
#100000
b0 /
0#
0&
#105000
0!
0"
b0 0
1#
#110000
0#
#115000
1#
#120000
0#
#125000
1#
#130000
b10 /
0#
1$
#135000
b100 /
b10 0
1#
#140000
b10 /
0#
0$
#145000
1#
#150000
b100 /
0#
1$
#155000
b110 /
b100 0
1#
#160000
b100 /
0#
0$
#165000
1#
#170000
b101 /
0#
1%
#175000
1"
b0 /
b101 0
1#
#180000
b0 /
0#
0%
#185000
0"
b0 0
1#
#190000
0#
#195000
1#
#200000
0#
#205000
1#
#210000
b10 /
0#
1$
#215000
b100 /
b10 0
1#
#220000
b10 /
0#
0$
#225000
1#
#230000
b110 /
0#
1&
#235000
1!
1"
b0 /
b110 0
1#
#240000
b0 /
0#
0&
#245000
0!
0"
b0 0
1#
