project 4/gate_controller.v
module parking_gate_fsm (
    input  wire clk,
    input  wire reset,
    input  wire car_detected,
    input  wire ticket_valid,
    input  wire car_passed,
    output reg  gate_open,
    output reg  gate_closed
);
    localparam IDLE = 3'b000;
    localparam CHECK_TICKET = 3'b001;
    localparam OPEN_GATE = 3'b010;
    localparam WAIT_FOR_CAR = 3'b011;
    localparam CLOSE_GATE = 3'b100;

    reg[2:0] state;
    reg[2:0] next_state;

    // - reset puts FSM in IDLE
    // - otherwise state <= next_state
    always @(posedge clk or posedge reset) begin
        if (reset) begin
            state <= IDLE;
        end 
        else begin
            state <= next_state;
        end 
    end

    // - default outputs
    // - default next_state
    // - case(state)
    // - define transitions and outputs
    always @(*) begin
        next_state = state;
        gate_open = 1'b0;
        gate_closed = 1'b1;

        case (state)
            IDLE: begin
                if (car_detected) begin
                    next_state = CHECK_TICKET;
                end
            end

            CHECK_TICKET: begin
                if (ticket_valid) begin
                    next_state = OPEN_GATE;
                end
                else begin
                    next_state = IDLE;
                end
            end

            OPEN_GATE: begin
                next_state = WAIT_FOR_CAR;
                gate_open = 1'b1;
                gate_closed = 1'b0;
            end

            WAIT_FOR_CAR: begin
                gate_open = 1'b1;
                gate_closed = 1'b0;

                if (car_passed) begin
                    next_state = CLOSE_GATE;
                end
            end

            CLOSE_GATE: begin
                next_state = IDLE;
            end

            default: begin
                next_state = IDLE;
                gate_open = 1'b0;
                gate_closed = 1'b1;
            end
        endcase
    end

endmodule

project 4/gate_controller_tb.v
`timescale 1ns / 1ps

module gate_controller_tb;

    reg clk;
    reg reset;
    reg car_detected;
    reg ticket_valid;
    reg car_passed;
    wire gate_open;
    wire gate_closed;

    parking_gate_fsm dut (
        .clk(clk),
        .reset(reset),
        .car_detected(car_detected),
        .ticket_valid(ticket_valid),
        .car_passed(car_passed),
        .gate_open(gate_open),
        .gate_closed(gate_closed)
    );

    initial begin
        clk = 1'b0;
    end

    always #5 clk = ~clk;

    initial begin
        $dumpfile("gate_controller_tb.vcd");
        $dumpvars(0, gate_controller_tb);

        reset        = 1'b1;
        car_detected = 1'b0;
        ticket_valid = 1'b0;
        car_passed   = 1'b0;

        #20;
        reset = 1'b0;

        // Car arrives and stays detected long enough for the FSM to sample it
        #10;
        car_detected = 1'b1;
        // Valid ticket is presented while FSM is in CHECK_TICKET
        ticket_valid = 1'b1;

        #20;
        car_detected = 1'b0;

        #20;
        ticket_valid = 1'b0;

        // Let FSM move through OPEN_GATE into WAIT_FOR_CAR
        #20;

        // Car passes only after gate has had time to open
        car_passed = 1'b1;

        #20;
        car_passed = 1'b0;

        // Let FSM close gate and return to IDLE
        #30;

        $finish;
    end

endmodule

project 4/gate_controller_tb.vcd
$date
	Thu Jun 18 09:37:23 2026
$end
$version
	Icarus Verilog
$end
$timescale
	1ps
$end
$scope module gate_controller_tb $end
$var wire 1 ! gate_open $end
$var wire 1 " gate_closed $end
$var reg 1 # car_detected $end
$var reg 1 $ car_passed $end
$var reg 1 % clk $end
$var reg 1 & reset $end
$var reg 1 ' ticket_valid $end
$scope module dut $end
$var wire 1 # car_detected $end
$var wire 1 $ car_passed $end
$var wire 1 % clk $end
$var wire 1 & reset $end
$var wire 1 ' ticket_valid $end
$var parameter 3 ( CHECK_TICKET $end
$var parameter 3 ) CLOSE_GATE $end
$var parameter 3 * IDLE $end
$var parameter 3 + OPEN_GATE $end
$var parameter 3 , WAIT_FOR_CAR $end
$var reg 1 " gate_closed $end
$var reg 1 ! gate_open $end
$var reg 3 - next_state [2:0] $end
$var reg 3 . state [2:0] $end
$upscope $end
$upscope $end
$enddefinitions $end
$comment Show the parameter values. $end
$dumpall
b11 ,
b10 +
b0 *
b100 )
b1 (
$end
#0
$dumpvars
b0 .
b0 -
0'
1&
0%
0$
0#
1"
0!
$end
#5000
1%
#10000
0%
#15000
1%
#20000
0%
0&
#25000
1%
#30000
b1 -
0%
1'
1#
#35000
b10 -
b1 .
1%
#40000
0%
#45000
0"
1!
b11 -
b10 .
1%
#50000
0"
1!
b11 -
0%
0#
#55000
0"
1!
b11 .
1%
#60000
0%
#65000
1%
#70000
0"
1!
0%
0'
#75000
1%
#80000
0%
#85000
1%
#90000
b100 -
0"
1!
0%
1$
#95000
b0 -
1"
0!
b100 .
1%
#100000
0%
#105000
b0 .
1%
#110000
0%
0$
