project 3/led_updown_counter.v
module led_updown_counter #(
    parameter LED_WIDTH = 8,
    parameter COUNT_WIDTH = 24
) (
    input wire clk,
    input wire reset,
    input wire enable,
    input wire direction,
    output reg [LED_WIDTH - 1: 0] leds
);

reg[COUNT_WIDTH - 1: 0] counter;
wire tick;

assign tick = (counter == {COUNT_WIDTH{1'b1}});

always @(posedge clk or posedge reset) begin
    // TODO: handle reset first
    if (reset) begin
        counter <= {COUNT_WIDTH{1'b0}};
        leds <= {LED_WIDTH{1'b0}};
    end

    // TODO: if enable is high, increment counter
    else if (enable) begin
        counter <= counter + 1'b1; 
        if (tick)  begin
            if (direction == 1'b0) begin
                leds <= leds + 1'b1;
            end 
            else begin
                leds <= leds - 1'b1;
            end
        end
    end
    else if (!enable) begin
        counter <= {COUNT_WIDTH{1'b0}};
    end
end

endmodule

project 3/led_updown_counter_tb.v
`timescale 1ns / 1ps

module led_updown_counter_tb;

    reg clk;
    reg reset;
    reg enable;
    reg direction;
    wire [3:0] leds;

    led_updown_counter #(
        .LED_WIDTH(4),
        .COUNT_WIDTH(3)
    ) dut (
        .clk(clk),
        .reset(reset),
        .enable(enable),
        .direction(direction),
        .leds(leds)
    );

    initial begin
        clk = 1'b0;
        forever #5 clk = ~clk;
    end

    initial begin
        $dumpfile("led_updown_counter_tb.vcd");
        $dumpvars(0, led_updown_counter_tb);

        reset = 1'b1;
        enable = 1'b0;
        direction = 1'b0;

        #20;
        reset = 1'b0;

        #10;
        enable = 1'b1;
        direction = 1'b0;   // count up

        #100;
        direction = 1'b1;   // count down

        #100;
        enable = 1'b0;      // hold

        #30;
        $finish;
    end

endmodule

project 3/led_updown_counter_tb.vcd
$date
	Tue Jun 16 04:34:10 2026
$end
$version
	Icarus Verilog
$end
$timescale
	1ps
$end
$scope module led_updown_counter_tb $end
$var wire 4 ! leds [3:0] $end
$var reg 1 " clk $end
$var reg 1 # direction $end
$var reg 1 $ enable $end
$var reg 1 % reset $end
$scope module dut $end
$var wire 1 " clk $end
$var wire 1 # direction $end
$var wire 1 $ enable $end
$var wire 1 % reset $end
$var wire 1 & tick $end
$var parameter 32 ' COUNT_WIDTH $end
$var parameter 32 ( LED_WIDTH $end
$var reg 3 ) counter [2:0] $end
$var reg 4 * leds [3:0] $end
$upscope $end
$upscope $end
$enddefinitions $end
$comment Show the parameter values. $end
$dumpall
b100 (
b11 '
$end
#0
$dumpvars
b0 *
b0 )
0&
1%
0$
0#
0"
b0 !
$end
#5000
1"
#10000
0"
#15000
1"
#20000
0"
0%
#25000
1"
#30000
0"
1$
#35000
b1 )
1"
#40000
0"
#45000
b10 )
1"
#50000
0"
#55000
b11 )
1"
#60000
0"
#65000
b100 )
1"
#70000
0"
#75000
b101 )
1"
#80000
0"
#85000
b110 )
1"
#90000
0"
#95000
1&
b111 )
1"
#100000
0"
#105000
b1 !
b1 *
0&
b0 )
1"
#110000
0"
#115000
b1 )
1"
#120000
0"
#125000
b10 )
1"
#130000
0"
1#
#135000
b11 )
1"
#140000
0"
#145000
b100 )
1"
#150000
0"
#155000
b101 )
1"
#160000
0"
#165000
b110 )
1"
#170000
0"
#175000
1&
b111 )
1"
#180000
0"
#185000
b0 !
b0 *
0&
b0 )
1"
#190000
0"
#195000
b1 )
1"
#200000
0"
#205000
b10 )
1"
#210000
0"
#215000
b11 )
1"
#220000
0"
#225000
b100 )
1"
#230000
0"
0$
